mulan/__init__.py
mulan/util.py
mulan/version.py
mulan/shell/__init__.py
mulan/shell/usage.py
mulan/src/temp.txt
mulan-0.0.3.dist-info/LICENSE
mulan-0.0.3.dist-info/METADATA
mulan-0.0.3.dist-info/WHEEL
mulan-0.0.3.dist-info/entry_points.txt
mulan-0.0.3.dist-info/top_level.txt
mulan-0.0.3.dist-info/zip-safe
mulan-0.0.3.dist-info/RECORD
