Metadata-Version: 2.1
Name: mulan
Version: 0.0.3
Summary: 木兰诗复读机
Home-page: https://github.com/Ailln/mulan
Author: Ailln
Author-email: kinggreenhall@gmail.com
License: MIT License
Platform: UNKNOWN
Classifier: Programming Language :: Python :: 3
Classifier: License :: OSI Approved :: MIT License
Classifier: Operating System :: OS Independent
Requires-Python: >=3.6
Requires-Dist: setuptools (>=40.6.3)
